{"front-end_hybrid.md":"nhj25M3p","basics_internet.md":"VcBcqYer","basics_http.md":"3jAMSobh","basics_make-up-principle.md":"JDgSG_Wg","front-end_basics_css_index.md":"dGgdLwxw","front-end_engineering_babel.md":"rhA0BnHI","front-end_browser.md":"IheZrakp","front-end_frame_jquery_index.md":"YHPzLHWd","front-end_engineering_pnpm.md":"7gdcO1tn","front-end_frame_react_index.md":"dAk0KaEU","front-end_engineering_webpack.md":"3yUKV6Vy","front-end_frame_index.md":"aRq5juTH","front-end_frame_vue_index.md":"ImP0wX60","index.md":"FsV6F089","front-end_design-patterns.md":"mPZA8XLS","basics_data-structures-algorithms_index.md":"aceD9zEI","basics_data-structures-algorithms_stack-queue.md":"nXjL7oaF","front-end_data-govern-exception-monitor.md":"YnSm0n_x","front-end_typescript_index.md":"s0ox_Dao","basics_data-structures-algorithms_linklist.md":"Lk-7WN7k","basics_data-structures-algorithms_heap-hash.md":"pzkID0gT","front-end_engineering_esbuild.md":"ebUQSFlj","front-end_micro-front-end.md":"gGbR1uVx","basics_os.md":"wXCAQ0Vn","basics_data-structures-algorithms_tree-graph.md":"iaeE6DHP","front-end_basics_javascript_index.md":"6-nrICez","front-end_engineering_eslint.md":"ZESilwKd","front-end_engineering_index.md":"obDBJR1O","basics_data-structures-algorithms_search-sort.md":"Ta4wrYgB","front-end_basics_html_index.md":"74lxO8pa","front-end_engineering_git.md":"9yXe9suX","front-end_basics_index.md":"X-Gjtnz9","basics_data-structures-algorithms_array-string.md":"0CAHKcmv","basics_data-structures-algorithms_dp-math.md":"yw1LXEVF"}
